worldapi/__init__.py
worldapi/main.py
worldapi-0.1.0.dist-info/LICENSE
worldapi-0.1.0.dist-info/METADATA
worldapi-0.1.0.dist-info/WHEEL
worldapi-0.1.0.dist-info/top_level.txt
worldapi-0.1.0.dist-info/RECORD
