Metadata-Version: 2.1
Name: worldapi
Version: 0.1.0
Summary: interacte with world
Home-page: https://github.com/engineering-wrench/WorldAPI
Author: EngeenerWerch
Author-email: cyberpony_x@mail.ru
Classifier: Programming Language :: Python :: 3
Classifier: License :: OSI Approved :: MIT License
Classifier: Operating System :: OS Independent
Requires-Python: >=3.6
License-File: LICENSE
